easy_udp/__init__.py
easy_udp/easyudp.py
easy_udp/easyudp_receiver.py
easy_udp/easyudp_sender.py
easy_udp/exceptions.py
examples/__init__.py
examples/receiver.py
examples/sender.py
easy_udp-0.1.10.dist-info/METADATA
easy_udp-0.1.10.dist-info/WHEEL
easy_udp-0.1.10.dist-info/top_level.txt
easy_udp-0.1.10.dist-info/RECORD
