Metadata-Version: 2.4
Name: easy_udp
Version: 0.1.10
Summary: Easy UDP communication library
Home-page: https://github.com/mookor/easyUDP
Author: Andrey Mazko
Requires-Dist: numpy
Dynamic: author
Dynamic: description
Dynamic: description-content-type
Dynamic: home-page
Dynamic: requires-dist
Dynamic: summary
